sklearn2pmml/__init__.py
sklearn2pmml/__main__.py
sklearn2pmml/cli.py
sklearn2pmml/configuration.py
sklearn2pmml/customization.py
sklearn2pmml/h2o.py
sklearn2pmml/metadata.py
sklearn2pmml/pycaret.py
sklearn2pmml/sklearn_pandas.py
sklearn2pmml/statsmodels.py
sklearn2pmml/tpot.py
sklearn2pmml/xgboost.py
sklearn2pmml/cross_reference/__init__.py
sklearn2pmml/decoration/__init__.py
sklearn2pmml/ensemble/__init__.py
sklearn2pmml/expression/__init__.py
sklearn2pmml/feature_extraction/__init__.py
sklearn2pmml/feature_extraction/text/__init__.py
sklearn2pmml/feature_selection/__init__.py
sklearn2pmml/metrics/__init__.py
sklearn2pmml/neural_network/__init__.py
sklearn2pmml/pipeline/__init__.py
sklearn2pmml/postprocessing/__init__.py
sklearn2pmml/preprocessing/__init__.py
sklearn2pmml/preprocessing/h2o.py
sklearn2pmml/preprocessing/lightgbm.py
sklearn2pmml/preprocessing/regex.py
sklearn2pmml/preprocessing/xgboost.py
sklearn2pmml/resources/__init__.py
sklearn2pmml/resources/classpath.txt
sklearn2pmml/resources/gson-2.13.2.jar
sklearn2pmml/resources/guava-33.5.0-jre.jar
sklearn2pmml/resources/h2o-genmodel-3.46.0.9.jar
sklearn2pmml/resources/h2o-logger-3.46.0.9.jar
sklearn2pmml/resources/h2o-tree-api-0.3.17.jar
sklearn2pmml/resources/istack-commons-runtime-4.1.2.jar
sklearn2pmml/resources/jackson-annotations-2.19.4.jar
sklearn2pmml/resources/jakarta.activation-api-2.1.4.jar
sklearn2pmml/resources/jakarta.xml.bind-api-4.0.4.jar
sklearn2pmml/resources/jaxb-core-4.0.6.jar
sklearn2pmml/resources/jaxb-runtime-4.0.6.jar
sklearn2pmml/resources/jcommander-1.82.jar
sklearn2pmml/resources/pickle-1.5.jar
sklearn2pmml/resources/pmml-converter-1.6.8.jar
sklearn2pmml/resources/pmml-h2o-1.3.4.jar
sklearn2pmml/resources/pmml-lightgbm-1.6.4.jar
sklearn2pmml/resources/pmml-model-1.7.6.jar
sklearn2pmml/resources/pmml-model-metro-1.7.6.jar
sklearn2pmml/resources/pmml-python-1.3.16.jar
sklearn2pmml/resources/pmml-sklearn-1.9.23.jar
sklearn2pmml/resources/pmml-sklearn-extension-1.9.23.jar
sklearn2pmml-0.125.2.dist-info/licenses/LICENSE.txt
sklearn2pmml-0.125.2.dist-info/licenses/NOTICE.txt
sklearn2pmml-0.125.2.dist-info/METADATA
sklearn2pmml-0.125.2.dist-info/WHEEL
sklearn2pmml-0.125.2.dist-info/entry_points.txt
sklearn2pmml-0.125.2.dist-info/top_level.txt
sklearn2pmml-0.125.2.dist-info/RECORD
