Metadata-Version: 2.4
Name: sklearn2pmml
Version: 0.125.2
Summary: Python library for converting Scikit-Learn pipelines to PMML
Home-page: https://github.com/jpmml/sklearn2pmml
Download-URL: https://github.com/jpmml/sklearn2pmml/archive/0.125.2.tar.gz
Author: Villu Ruusmann
Author-email: villu.ruusmann@gmail.com
License: GNU Affero General Public License (AGPL) version 3.0
Classifier: Development Status :: 5 - Production/Stable
Classifier: Operating System :: OS Independent
Classifier: Programming Language :: Python
Classifier: Intended Audience :: Developers
Classifier: Intended Audience :: Science/Research
Classifier: Topic :: Software Development
Classifier: Topic :: Scientific/Engineering
Requires-Python: >=3.8
License-File: LICENSE.txt
License-File: NOTICE.txt
Requires-Dist: dill>=0.3.4
Requires-Dist: joblib>=0.13.0
Requires-Dist: pandas>=1.5.0
Requires-Dist: scikit-learn>=1.0
Dynamic: author
Dynamic: author-email
Dynamic: classifier
Dynamic: download-url
Dynamic: home-page
Dynamic: license
Dynamic: license-file
Dynamic: requires-dist
Dynamic: requires-python
Dynamic: summary
